test_junkie/__init__.py
test_junkie/__main__.py
test_junkie/builder.py
test_junkie/compatability_utils.py
test_junkie/constants.py
test_junkie/debugger.py
test_junkie/decorators.py
test_junkie/errors.py
test_junkie/listener.py
test_junkie/meta.py
test_junkie/metrics.py
test_junkie/objects.py
test_junkie/parallels.py
test_junkie/rules.py
test_junkie/runner.py
test_junkie/settings.py
test_junkie/cli/__init__.py
test_junkie/cli/cli.py
test_junkie/cli/cli_audit.py
test_junkie/cli/cli_config.py
test_junkie/cli/cli_runner.py
test_junkie/reporter/__init__.py
test_junkie/reporter/analyzer.py
test_junkie/reporter/html_reporter.py
test_junkie/reporter/html_template.py
test_junkie/reporter/xml_reporter.py
tests/QualityManager.py
tests/__init__.py
tests/test_advanced_features.py
tests/test_basic_features.py
tests/test_threading.py
tests/after_class/__init__.py
tests/after_class/test_reporting_on_assertion.py
tests/after_class/test_reporting_on_exception.py
tests/before_class/__init__.py
tests/before_class/test_before_group_rules.py
tests/before_class/test_ignore_on_assertion.py
tests/before_class/test_ignore_on_exception.py
tests/cli/CliTestSuite.py
tests/cli/Cmd.py
tests/cli/__init__.py
tests/cli/test_cli.py
tests/cli_edge/InportSuite.py
tests/cli_edge/InterruptSuite.py
tests/cli_edge/__init__.py
tests/cli_edge/test_cli_edge.py
tests/junkie_suites/AdvancedSuite.py
tests/junkie_suites/AfterClassAssertionSuite.py
tests/junkie_suites/AfterClassExceptionSuite.py
tests/junkie_suites/AfterTestAssertionSuite.py
tests/junkie_suites/AfterTestExceptionSuite.py
tests/junkie_suites/BasicSuite.py
tests/junkie_suites/BeforeClassAssertionSuite.py
tests/junkie_suites/BeforeClassExceptionSuite.py
tests/junkie_suites/BeforeTestAssertionSuite.py
tests/junkie_suites/BeforeTestExceptionSuite.py
tests/junkie_suites/CancelSuite.py
tests/junkie_suites/Constants.py
tests/junkie_suites/ExecutionSquence.py
tests/junkie_suites/FeatureAggregations.py
tests/junkie_suites/IgnoreSuite.py
test_junkie-0.8a8.dist-info/LICENCE
test_junkie-0.8a8.dist-info/METADATA
test_junkie-0.8a8.dist-info/WHEEL
test_junkie-0.8a8.dist-info/entry_points.txt
test_junkie-0.8a8.dist-info/top_level.txt
test_junkie-0.8a8.dist-info/RECORD
