Metadata-Version: 2.1
Name: test-junkie
Version: 0.8a8
Summary: Modern Testing Framework
Home-page: https://www.test-junkie.com/
Author: Artur Spirin
Author-email: as.no.replies@gmail.com
License: UNKNOWN
Keywords: automation,testing,tests,test-runner
Platform: UNKNOWN
Classifier: Development Status :: 3 - Alpha
Classifier: Intended Audience :: Developers
Classifier: Programming Language :: Python :: 2.7
Classifier: Programming Language :: Python :: 3.5
Classifier: Programming Language :: Python :: 3.6
Classifier: Programming Language :: Python :: 3.7
Classifier: Programming Language :: Python :: 3.8
Classifier: Programming Language :: Python :: 3.9
Classifier: Programming Language :: Python :: 3.10
Classifier: License :: OSI Approved :: MIT License
Classifier: Operating System :: OS Independent
Classifier: Topic :: Software Development :: Quality Assurance
Classifier: Topic :: Software Development :: Testing
Classifier: Topic :: Software Development :: Libraries
Classifier: Topic :: Software Development :: Libraries :: Python Modules
Classifier: Topic :: Utilities
License-File: LICENCE
Requires-Dist: statistics
Requires-Dist: psutil
Requires-Dist: appdirs
Requires-Dist: configparser
Requires-Dist: colorama
Requires-Dist: coverage
